{"last_time": 1745134047.0368843, "lat": -113.924425, "lon": 51.259113199999994, "rel_alt": 100.013, "alt": 1212.23, "roll": 0.26111865043640137, "pitch": 0.026647262275218964, "yaw": -2.5491557121276855, "dlat": -10.04, "dlon": -19.02, "dalt": -0.04, "heading": 213.95, "airspeed": 0.0, "groundspeed": 21.514801025390625, "throttle": 64.0, "climb": 0.04192829504609108, "num_satellites": 24.0, "position_uncertainty": 383.0, "alt_uncertainty": 625.0, "speed_uncertainty": 129.0, "heading_uncertainty": 0.0, "flight_mode": 10.0, "battery_voltage": 23265.0, "battery_current": 3531.0, "battery_remaining": 81.0}