{"last_time": 1745134168.1826463, "lat": -113.9269573, "lon": 51.262453099999995, "rel_alt": 99.943, "alt": 1212.16, "roll": 0.08493326604366302, "pitch": 0.027611032128334045, "yaw": 1.9109916687011719, "dlat": -2.73, "dlon": 13.6, "dalt": 0.52, "heading": 109.49, "airspeed": 0.0, "groundspeed": 13.881726264953613, "throttle": 64.0, "climb": -0.52952641248703, "num_satellites": 24.0, "position_uncertainty": 399.0, "alt_uncertainty": 624.0, "speed_uncertainty": 124.0, "heading_uncertainty": 0.0, "flight_mode": 10.0, "battery_voltage": 22857.0, "battery_current": 3414.0, "battery_remaining": 67.0}