{"last_time": 1745134408.6753619, "lat": -113.9301251, "lon": 51.2609493, "rel_alt": 0.071, "alt": 1112.53, "roll": -0.024774283170700073, "pitch": 0.15813279151916504, "yaw": 2.3329946994781494, "dlat": 0.0, "dlon": 0.0, "dalt": 0.0, "heading": 133.67, "airspeed": 0.0, "groundspeed": 0.006013010162860155, "throttle": 0.0, "climb": -0.0008630465599708259, "num_satellites": 25.0, "position_uncertainty": 322.0, "alt_uncertainty": 496.0, "speed_uncertainty": 157.0, "heading_uncertainty": 0.0, "flight_mode": 5.0, "battery_voltage": 23282.0, "battery_current": 3.0, "battery_remaining": 52.0}