{"last_time": 1745135809.9402256, "lat": -113.927064, "lon": 51.2614327, "rel_alt": 30.705, "alt": 1143.47, "roll": -0.06287775933742523, "pitch": -0.024878934025764465, "yaw": 2.159428358078003, "dlat": -8.63, "dlon": 14.32, "dalt": -0.54, "heading": 123.72, "airspeed": 0.0, "groundspeed": 16.724788665771484, "throttle": 61.0, "climb": 0.5488198399543762, "num_satellites": 25.0, "position_uncertainty": 437.0, "alt_uncertainty": 678.0, "speed_uncertainty": 133.0, "heading_uncertainty": 0.0, "flight_mode": 10.0, "battery_voltage": 23708.0, "battery_current": 3144.0, "battery_remaining": 84.0}