{"last_time": 1745135842.3191025, "lat": -113.9261556, "lon": 51.259323699999996, "rel_alt": 29.291, "alt": 1142.06, "roll": 0.3755244016647339, "pitch": 0.048216912895441055, "yaw": -1.7708200216293335, "dlat": 4.8, "dlon": -25.32, "dalt": 0.02, "heading": 258.54, "airspeed": 0.0, "groundspeed": 25.779348373413086, "throttle": 68.0, "climb": -0.027506843209266663, "num_satellites": 26.0, "position_uncertainty": 385.0, "alt_uncertainty": 632.0, "speed_uncertainty": 107.0, "heading_uncertainty": 0.0, "flight_mode": 10.0, "battery_voltage": 23569.0, "battery_current": 4209.0, "battery_remaining": 81.0}