{"last_time": 1745135879.2489839, "lat": -113.92366489999999, "lon": 51.261192, "rel_alt": 30.053, "alt": 1142.82, "roll": 0.6248903274536133, "pitch": 0.03603546321392059, "yaw": 1.7422564029693604, "dlat": -2.59, "dlon": 16.45, "dalt": 0.98, "heading": 99.82, "airspeed": 0.0, "groundspeed": 16.654123306274414, "throttle": 70.0, "climb": -0.9868993759155273, "num_satellites": 27.0, "position_uncertainty": 385.0, "alt_uncertainty": 641.0, "speed_uncertainty": 154.0, "heading_uncertainty": 0.0, "flight_mode": 10.0, "battery_voltage": 23431.0, "battery_current": 4604.0, "battery_remaining": 78.0}