{"last_time": 1745135904.8001952, "lat": -113.92870909999999, "lon": 51.2599096, "rel_alt": 28.347, "alt": 1141.11, "roll": 0.7705557346343994, "pitch": 0.13150835037231445, "yaw": -1.1156847476959229, "dlat": 18.0, "dlon": -21.3, "dalt": 0.33, "heading": 296.08, "airspeed": 0.0, "groundspeed": 27.895740509033203, "throttle": 82.0, "climb": -0.33866944909095764, "num_satellites": 25.0, "position_uncertainty": 372.0, "alt_uncertainty": 626.0, "speed_uncertainty": 154.0, "heading_uncertainty": 0.0, "flight_mode": 10.0, "battery_voltage": 23058.0, "battery_current": 7191.0, "battery_remaining": 75.0}