{"last_time": 1745133990.0672317, "lat": -113.9267742, "lon": 51.2600372, "rel_alt": 100.364, "alt": 1212.58, "roll": 0.20322558283805847, "pitch": 0.02921265736222267, "yaw": -0.8580635190010071, "dlat": 19.2, "dlon": -21.23, "dalt": -0.76, "heading": 310.84, "airspeed": 0.0, "groundspeed": 28.63800048828125, "throttle": 61.0, "climb": 0.7620615363121033, "num_satellites": 24.0, "position_uncertainty": 377.0, "alt_uncertainty": 629.0, "speed_uncertainty": 130.0, "heading_uncertainty": 0.0, "flight_mode": 10.0, "battery_voltage": 23313.0, "battery_current": 3122.0, "battery_remaining": 86.0}