{"last_time": 1745134094.9887981, "lat": -113.92655169999999, "lon": 51.2610275, "rel_alt": 99.595, "alt": 1211.81, "roll": 0.010030586272478104, "pitch": 0.03313504904508591, "yaw": 2.405081033706665, "dlat": -9.43, "dlon": 6.76, "dalt": 0.47, "heading": 137.8, "airspeed": 0.0, "groundspeed": 11.605815887451172, "throttle": 63.0, "climb": -0.47999972105026245, "num_satellites": 24.0, "position_uncertainty": 378.0, "alt_uncertainty": 639.0, "speed_uncertainty": 128.0, "heading_uncertainty": 0.0, "flight_mode": 10.0, "battery_voltage": 23185.0, "battery_current": 3461.0, "battery_remaining": 76.0}