{"last_time": 1745134101.9689584, "lat": -113.9258486, "lon": 51.2605083, "rel_alt": 99.714, "alt": 1211.93, "roll": 0.0968286395072937, "pitch": 0.038473986089229584, "yaw": 2.379575729370117, "dlat": -7.8, "dlon": 6.92, "dalt": 0.01, "heading": 136.33, "airspeed": 0.0, "groundspeed": 10.43391227722168, "throttle": 63.0, "climb": -0.014570913277566433, "num_satellites": 24.0, "position_uncertainty": 376.0, "alt_uncertainty": 637.0, "speed_uncertainty": 130.0, "heading_uncertainty": 0.0, "flight_mode": 10.0, "battery_voltage": 23153.0, "battery_current": 3424.0, "battery_remaining": 75.0}