{"last_time": 1745134111.7526248, "lat": -113.92491249999999, "lon": 51.259812, "rel_alt": 100.443, "alt": 1212.66, "roll": 0.0645560473203659, "pitch": 0.04423706233501434, "yaw": 2.3069286346435547, "dlat": -7.82, "dlon": 6.76, "dalt": -0.34, "heading": 132.17, "airspeed": 0.0, "groundspeed": 10.343001365661621, "throttle": 63.0, "climb": 0.34448572993278503, "num_satellites": 25.0, "position_uncertainty": 380.0, "alt_uncertainty": 627.0, "speed_uncertainty": 130.0, "heading_uncertainty": 0.0, "flight_mode": 10.0, "battery_voltage": 23143.0, "battery_current": 3440.0, "battery_remaining": 74.0}