{"last_time": 1745134185.3059196, "lat": -113.9251453, "lon": 51.2609911, "rel_alt": 100.382, "alt": 1212.6, "roll": 0.05188079550862312, "pitch": 0.021240003407001495, "yaw": 2.3255045413970947, "dlat": -8.74, "dlon": 7.49, "dalt": -0.01, "heading": 133.24, "airspeed": 0.0, "groundspeed": 11.520788192749023, "throttle": 59.0, "climb": 0.014048699289560318, "num_satellites": 24.0, "position_uncertainty": 366.0, "alt_uncertainty": 602.0, "speed_uncertainty": 131.0, "heading_uncertainty": 0.0, "flight_mode": 10.0, "battery_voltage": 22970.0, "battery_current": 2857.0, "battery_remaining": 65.0}