{"last_time": 1745134202.7130852, "lat": -113.92366369999999, "lon": 51.2595664, "rel_alt": 99.757, "alt": 1211.97, "roll": 0.5301413536071777, "pitch": 0.051542479544878006, "yaw": 2.984192371368408, "dlat": -14.55, "dlon": -4.59, "dalt": 0.43, "heading": 170.98, "airspeed": 0.0, "groundspeed": 15.264209747314453, "throttle": 68.0, "climb": -0.4364176392555237, "num_satellites": 25.0, "position_uncertainty": 439.0, "alt_uncertainty": 667.0, "speed_uncertainty": 133.0, "heading_uncertainty": 0.0, "flight_mode": 10.0, "battery_voltage": 22779.0, "battery_current": 4083.0, "battery_remaining": 64.0}