{"last_time": 1745135814.6030235, "lat": -113.92604499999999, "lon": 51.2612083, "rel_alt": 31.089, "alt": 1143.85, "roll": -0.024783730506896973, "pitch": -0.03226553648710251, "yaw": 1.9120349884033203, "dlat": -2.72, "dlon": 16.47, "dalt": 0.66, "heading": 109.55, "airspeed": 0.0, "groundspeed": 16.70085334777832, "throttle": 57.0, "climb": -0.669198215007782, "num_satellites": 26.0, "position_uncertainty": 400.0, "alt_uncertainty": 649.0, "speed_uncertainty": 125.0, "heading_uncertainty": 0.0, "flight_mode": 10.0, "battery_voltage": 23819.0, "battery_current": 2444.0, "battery_remaining": 84.0}