{"last_time": 1745135890.800161, "lat": -113.9244106, "lon": 51.2597666, "rel_alt": 29.89, "alt": 1142.66, "roll": -0.041309721767902374, "pitch": -0.0032915696501731873, "yaw": -2.681565046310425, "dlat": -12.59, "dlon": -13.19, "dalt": 0.14, "heading": 206.36, "airspeed": 0.0, "groundspeed": 18.239089965820312, "throttle": 59.0, "climb": -0.14044101536273956, "num_satellites": 26.0, "position_uncertainty": 392.0, "alt_uncertainty": 638.0, "speed_uncertainty": 124.0, "heading_uncertainty": 0.0, "flight_mode": 10.0, "battery_voltage": 23634.0, "battery_current": 2893.0, "battery_remaining": 77.0}